LICENSE.txt
README.md
setup.py
lus/LosFile.py
lus/__main__.py
lus.egg-info/PKG-INFO
lus.egg-info/SOURCES.txt
lus.egg-info/dependency_links.txt
lus.egg-info/entry_points.txt
lus.egg-info/requires.txt
lus.egg-info/top_level.txt