Metadata-Version: 2.4
Name: lus
Version: 0.1.0
Summary: A simple task-runner using KDL for configuration
Home-page: https://bixense.com/lus
Download-URL: https://github.com/jhasse/lus/archive/v0.1.0.tar.gz
Author: Jan Niklas Hasse
Author-email: jhasse@bixense.com
License-File: LICENSE.txt
Requires-Dist: ckdl
Dynamic: author
Dynamic: author-email
Dynamic: download-url
Dynamic: home-page
Dynamic: license-file
Dynamic: requires-dist
Dynamic: summary
